{
  "id": "arur_haman_em",
  "sections": [
    {
      "text": [
        "אָרוּר הָמָן בָּרוּךְ מָרְדְּכַי.",
        "אֲרוּרָה זֶרֶשׁ בְּרוּכָה אֶסְתֵּר.",
        "אֲרוּרִים כָּל הָרְשָׁעִים בְּרוּכִים כָּל יִשְׂרָאֵל, וְגַם חַרְבוֹנָה זָכוּר לַטּוֹב:",
        "אָרוּר הָמָן בָּרוּךְ מָרְדְּכַי.",
        "אֲרוּרָה זֶרֶשׁ בְּרוּכָה אֶסְתֵּר.",
        "אֲרוּרִים כָּל הָרְשָׁעִים בְּרוּכִים כָּל יִשְׂרָאֵל, וְגַם חַרְבוֹנָה זָכוּר לַטּוֹב:",
        "אָרוּר הָמָן בָּרוּךְ מָרְדְּכַי.",
        "אֲרוּרָה זֶרֶשׁ בְּרוּכָה אֶסְתֵּר.",
        "אֲרוּרִים כָּל הָרְשָׁעִים בְּרוּכִים כָּל יִשְׂרָאֵל, וְגַם חַרְבוֹנָה זָכוּר לַטּוֹב:"
      ],
      "condition_flags": [],
      "exclude_flags": []
    }
  ]
}
