{
  "id": "seder_tefillin",
  "sections": [
    {
      "text": [
        "לְשֵׁם יִחוּד קֻדְשָׁא בְּרִיךְ הוּא וּשְׁכִינְתֵּיהּ,",
        "בִּדְחִילוּ וּרְחִימוּ, וּרְחִימוּ וּדְחִילוּ,",
        "לְיַחֲדָא שֵׁם יוֹ\"ד קֵ\"י בְּוָא\"ו קֵ\"י בְּיִחוּדָא שְׁלִים (יהוה) בְּשֵׁם",
        "כָּל־יִשְׂרָאֵל.",
        "הֲרֵינִי מוּכָן לְקַיֵּם מִצְוַת עֲשֵׂה לְהָנִיחַ תְּפִלִּין בְּיָדִי",
        "וּבְרֹאשִׁי, כְּמוֹ שֶׁצִּוָּנוּ יְהֹוָה אֱלֹהֵֽינוּ:",
        "(דברים יא יח) וּקְשַׁרְתֶּם אֹתָם לְאוֹת עַל־יֶדְכֶם וְהָיוּ לְטוֹטָפֹת",
        "בֵּין עֵינֵיכֶֽם.",
        "וְצִוָּנוּ הַקָּדוֹשׁ בָּרוּךְ הוּא לְהָנִיחַ אַרְבַּע פַּרְשִׁיּוֹת אֵלּוּ",
        "שֶׁיֵּשׁ בָּהֶם יִחוּד שְׁמוֹ וִיצִיאַת מִצְרַיִם עַל הַזְּרוֹעַ כְּנֶגֶד",
        "הַלֵּב, וְעַל הָרֹאשׁ כְּנֶגֶד הַמֹּחַ,",
        "כְּדֵי שֶׁנִּזְכֹּר נִסִּים וְנִפְלָאוֹת שֶׁעָשָׂה עִמָּנוּ.",
        "וַהֲרֵינִי מוּכָן לְבָרֵךְ הַבְּרָכָה שֶׁתִּקְנוּ רַבּוֹתֵינוּ זִכְרוֹנָם",
        "לִבְרָכָה עַל מִצְוַת הַתְּפִלִּין,",
        "וַהֲרֵינִי מְכַוֵּן לִפְטֹר בִּבְרָכָה זוֹ תְּפִלִּין שֶׁל יָד וּתְפִלִּין",
        "שֶׁל רֹאשׁ,",
        "וְיַעֲלֶה לְפָנֶיךָ יְהֹוָה אֱלֹהֵֽינוּ וֵאלהֵי אֲבוֹתֵינוּ כְּאִלּוּ",
        "כִּוַּנְתִּי בְּכָל הַכַּוָּנוֹת הָרְאוּיוֹת לְכַוֵּן בַּהֲנָחַת",
        "הַתְּפִלִּין וּבַבְּרָכָה.",
        "וִיהִי ׀ נֹעַם אֲדֹנָי אֱלֹהֵינוּ עָלֵינוּ וּמַעֲשֵׂה יָדֵינוּ כּוֹנְנָה",
        "עָלֵינוּ וּֽמַעֲשֵׂה יָדֵינוּ כּוֹנְנֵֽהוּ׃"
      ],
      "condition_flags": [],
      "exclude_flags": []
    },
    {
      "text": [
        "יניח תפילין של יד על קיבורת ידו, וקודם שיהדק יברך:"
      ],
      "condition_flags": [],
      "exclude_flags": []
    },
    {
      "text": [
        "בָּרוּךְ אַתָּה יְהֹוָה, אֱלֹהֵינוּ מֶלֶךְ הָעוֹלָם,",
        "אֲשֶׁר קִדְּשָׁנוּ בְּמִצְוֹתָיו, וְצִוָּנוּ לְהָנִיחַ תְּפִלִּין:"
      ],
      "condition_flags": [],
      "exclude_flags": []
    },
    {
      "text": [
        "ואחר כך מניח של ראש בלא ברכה (אלא אם הפסיק בין יד לראש שאז מברך):"
      ],
      "condition_flags": [],
      "exclude_flags": []
    },
    {
      "text": [
        "בָּרוּךְ אַתָּה יְהֹוָה, אֱלֹהֵינוּ מֶלֶךְ הָעוֹלָם,",
        "אֲשֶׁר קִדְּשָׁנוּ בְּמִצְוֹתָיו, וְצִוָּנוּ עַל מִצְוַת תְּפִלִּין:"
      ],
      "condition_flags": [
        "hefsek_tefillin"
      ],
      "exclude_flags": []
    }
  ]
}
