{
  "id": "bhm_em_rachem",
  "sections": [
    {
      "text": [
        "רַחֵם יְהֹוָה אֱלֹהֵֽינוּ עָלֵֽינוּ וְעַל יִשְׂרָאֵל עַמָּךְ, וְעַל יְרוּשָׁלַֽיִם עִירָךְ,",
        "וְעַל הַר צִיּוֹן מִשְׁכַּן כְּבוֹדָךְ, וְעַל הֵיכָלָךְ, וְעַל מְעוֹנָךְ, וְעַל דְּבִירָךְ,",
        "וְעַל הַבַּֽיִת הַגָּדוֹל וְהַקָּדוֹשׁ שֶׁנִּקְרָא שִׁמְךָ עָלָיו.",
        "אָבִֽינוּ, רְעֵֽנוּ, זוּנֵֽנוּ, פַּרְנְסֵֽנוּ, כַּלְכְּלֵֽנוּ, הַרְוִיחֵֽנוּ הַרְוַח־לָֽנוּ מְהֵרָה מִכָּל־צָרוֹתֵֽינוּ.",
        "וְנָא, אַל תַּצְרִיכֵֽנוּ יְהֹוָה אֱלֹהֵֽינוּ, לִידֵי מַתְּנוֹת בָּשָׂר וָדָם וְלֹא לִידֵי הַלְוָאָתָם,",
        "אֶלָּא לְיָֽדְךָֽ הַמְּלֵאָה וְהָרְחָבָה, הָעֲשִׁירָה וְהַפְּתוּחָה,",
        "יְהִי רָצוֹן שֶׁלֹּא נֵבוֹשׁ בָּעוֹלָם הַזֶּה, וְלֹא נִכָּלֵם לָעוֹלָם הַבָּא,",
        "וּמַלְכוּת בֵּית דָּוִד מְשִׁיחָךְ תַּחֲזִירֶֽנָּה לִמְקוֹמָהּ בִּמְהֵרָה בְיָמֵֽינוּ:"
      ],
      "condition_flags": [],
      "exclude_flags": []
    }
  ]
}